{
  "name": "vite-project",
  "private": true,
  "version": "0.0.0",
  "type": "module",
  "scripts": {
    "dev": "vite",
    "build": "vite build",
    "preview": "vite preview",
    "serve": "vite serve",
    
  },
  "devDependencies": {
    "@vitejs/plugin-react": "^4.3.4",
    "typescript": "~5.6.2",
    "vite": "^6.0.11"
  },
  "dependencies": {
    "@types/react": "^19.0.8",
    "@types/react-dom": "^19.0.3",
    "react": "^19.0.0",
    "react-dom": "^19.0.0"
  },
  "description": "导入时不使用花括号 {}，并且可以使用任意名称",
  "main": "vite.config.js",
  "author": "",
  "license": "ISC",
  "eslintConfig": {
    "extends": [
      "plugin:react/recommended",
      "plugin:@typescript-eslint/recommended"
    ],
    "parser": "@typescript-eslint/parser",
    "plugins": [
      "@typescript-eslint"
    ]
  },
  "prettier": {
    "semi": false,
    "singleQuote": true
  },
  "resolutions": {
    "markdownlint-config-schema": "./.vscode/markdownlint-config-schema.json"
  }
}

